fastlogger/__init__.py
fastlogger/handlers.py
fastlogger/settings.py
fastlogger/setup.py
fastlogger-0.2.0.dist-info/WHEEL
fastlogger-0.2.0.dist-info/METADATA
fastlogger-0.2.0.dist-info/RECORD
